{
    "compilerOptions": {
        "strictNullChecks": false,
        "allowUnreachableCode": true,
        "sourceMap": true,
        "removeComments": true,
        "allowSyntheticDefaultImports": true,
        "noFallthroughCasesInSwitch": true,
        "importHelpers": true,
        "target": "es5",
        "lib": [
            "dom",
            "dom.iterable",
            "esnext"
        ],
        "allowJs": true,
        "skipLibCheck": true,
        "strict": true,
        "forceConsistentCasingInFileNames": true,
        "noEmit": true,
        "esModuleInterop": true,
        "module": "esnext",
        "moduleResolution": "node",
        "resolveJsonModule": true,
        "isolatedModules": true,
        "jsx": "preserve",
        "baseUrl": ".",
        "experimentalDecorators": true,
        "incremental": true,
        "composite": false,
        "newLine": "lf",
        "declaration": true,
        "declarationMap": true,
        "noImplicitAny": true,
        "noImplicitReturns": true,
        "noUncheckedIndexedAccess": true,
        "noUnusedLocals": true,
        "noUnusedParameters": true,
        "noImplicitOverride": true
    }
}
